google_translate_django4/__init__.py
google_translate_django4/admin.py
google_translate_django4/apps.py
google_translate_django4/models.py
google_translate_django4/tests.py
google_translate_django4/views.py
google_translate_django4-0.5.dist-info/LICENSE.txt
google_translate_django4-0.5.dist-info/METADATA
google_translate_django4-0.5.dist-info/WHEEL
google_translate_django4-0.5.dist-info/top_level.txt
google_translate_django4-0.5.dist-info/RECORD
