Metadata-Version: 2.1
Name: google-translate-django4
Version: 0.5
Summary: The working google translate module for Django version 4 and above
Home-page: https://github.com/webprice/google_translate_django4
Download-URL: https://github.com/webprice/google_translate_django4/archive/refs/heads/main.zip
Author: Serhii Hrekov
Author-email: admin@broplanner.com
License: MIT
Keywords: Django translate,Django Google Translate,Google translate
Classifier: Development Status :: 5 - Production/Stable
Classifier: Intended Audience :: Developers
Classifier: Topic :: Software Development :: Build Tools
Classifier: License :: OSI Approved :: MIT License
Classifier: Programming Language :: Python :: 3
Classifier: Programming Language :: Python :: 3.4
Classifier: Programming Language :: Python :: 3.5
Classifier: Programming Language :: Python :: 3.6
Classifier: Programming Language :: Python :: 3.7
Classifier: Programming Language :: Python :: 3.8
Classifier: Programming Language :: Python :: 3.9
License-File: LICENSE.txt
Requires-Dist: django
